generate_corr_sequence/__init__.py
generate_corr_sequence/generate_corr_sequence.py
generate_corr_sequence-0.1.1.dist-info/METADATA
generate_corr_sequence-0.1.1.dist-info/WHEEL
generate_corr_sequence-0.1.1.dist-info/licenses/LICENSE
generate_corr_sequence-0.1.1.dist-info/RECORD
