Metadata-Version: 2.1
Name: generate_corr_sequence
Version: 0.1.1
Summary: Generate correlated random samples
Project-URL: Homepage, https://github.com/bykhov/generate_corr_sequence
Author: Dima Bykhovsky, Netanel Tochilovsky, Alexander Rudyak
License: Copyright (c) 2023 The Python Packaging Authority
License-File: LICENSE
Keywords: autocorrelation,distribution,random process,random variable,simulation,stationary,time series
Classifier: License :: OSI Approved :: MIT License
Classifier: Operating System :: OS Independent
Classifier: Programming Language :: Python :: 3
Requires-Python: >=3.7
Requires-Dist: matplotlib
Requires-Dist: numpy
Requires-Dist: scipy
Requires-Dist: statsmodels
